src/__init__.py
terminus_tool/__init__.py
terminus_tool-0.5.7.data/scripts/terminus
terminus_tool-0.5.7.dist-info/DESCRIPTION.rst
terminus_tool-0.5.7.dist-info/METADATA
terminus_tool-0.5.7.dist-info/RECORD
terminus_tool-0.5.7.dist-info/WHEEL
terminus_tool-0.5.7.dist-info/metadata.json
terminus_tool-0.5.7.dist-info/top_level.txt
