Metadata-Version: 2.0
Name: terminus-tool
Version: 0.5.7
Summary: Experimental C/C++ source package manager
Home-page: https://github.com/tcmug/terminus
Author: tcmug
Author-email: teemu.merikoski@gmail.com
License: MIT
Platform: UNKNOWN
Requires-Python: >=3
Requires-Dist: pyyaml (>=3.12)
